cleasy/__init__.py
cleasy/config.py
cleasy/decorators.py
cleasy/shell.py
cleasy/style.py
cleasy-1.0.0.dist-info/LICENSE
cleasy-1.0.0.dist-info/METADATA
cleasy-1.0.0.dist-info/WHEEL
cleasy-1.0.0.dist-info/top_level.txt
cleasy-1.0.0.dist-info/RECORD
