Metadata-Version: 2.1
Name: cleasy
Version: 1.0.0
Summary: Simple CLI shell
Home-page: https://github.com/sergeport/cleasy
Author: Sergii Bibikov
Author-email: sergeport@gmail.com
License: UNKNOWN
Platform: UNKNOWN
Classifier: Programming Language :: Python :: 3
Classifier: License :: OSI Approved :: MIT License
Classifier: Operating System :: OS Independent
Requires-Dist: PyInquirer (==1.0.3)
Provides-Extra: prettyfy_output
Requires-Dist: termcolor (==1.1.0) ; extra == 'prettyfy_output'
Requires-Dist: pyfiglet (==0.8.post1) ; extra == 'prettyfy_output'
